ffmpeg_installer/__init__.py
ffmpeg_installer/install_ffmpeg.py
ffmpeg_installer-0.1.1.dist-info/METADATA
ffmpeg_installer-0.1.1.dist-info/WHEEL
ffmpeg_installer-0.1.1.dist-info/entry_points.txt
ffmpeg_installer-0.1.1.dist-info/top_level.txt
ffmpeg_installer-0.1.1.dist-info/RECORD
